qsubwt/__init__.py
qsubwt/qsubwt.py
qsubwt/version.py
qsubwt-1.0.2.dist-info/LICENSE
qsubwt-1.0.2.dist-info/METADATA
qsubwt-1.0.2.dist-info/WHEEL
qsubwt-1.0.2.dist-info/entry_points.txt
qsubwt-1.0.2.dist-info/top_level.txt
qsubwt-1.0.2.dist-info/RECORD
