Metadata-Version: 2.1
Name: qsubwt
Version: 1.0.2
Home-page: https://github.com/yodeng/qsubwt.git
Author: Deng Yong
Author-email: yodeng@tju.edu.cn
License: MIT
Requires-Python: >=3.5
License-File: LICENSE
